flytekitplugins_perian_job-1.16.12-py3.14-nspkg.pth
flytekitplugins/perian_job/__init__.py
flytekitplugins/perian_job/connector.py
flytekitplugins/perian_job/task.py
flytekitplugins_perian_job-1.16.12.dist-info/METADATA
flytekitplugins_perian_job-1.16.12.dist-info/WHEEL
flytekitplugins_perian_job-1.16.12.dist-info/entry_points.txt
flytekitplugins_perian_job-1.16.12.dist-info/namespace_packages.txt
flytekitplugins_perian_job-1.16.12.dist-info/top_level.txt
flytekitplugins_perian_job-1.16.12.dist-info/RECORD
